loaderinsta.py
loaderinsta-0.0.1.dist-info/WHEEL
loaderinsta-0.0.1.dist-info/METADATA
loaderinsta-0.0.1.dist-info/RECORD
