Metadata-Version: 2.1
Name: loaderinsta
Version: 0.0.1
Summary: Instagram post yuklash
Author: Brodyaga
Requires-Python: >=3.10,<4.0
Classifier: Programming Language :: Python :: 3
Classifier: Programming Language :: Python :: 3.10
